pytrim/__init__.py
pytrim/import_mappings.json
pytrim/py.typed
pytrim/analyzers/__init__.py
pytrim/analyzers/dependency_analyzer.py
pytrim/analyzers/module_analyzer.py
pytrim/call_graph_generator/__init__.py
pytrim/call_graph_generator/find_direct_and_unused_deps.py
pytrim/call_graph_generator/find_undeclared_deps.py
pytrim/call_graph_generator/generate_cg.py
pytrim/call_graph_generator/dependency_resolution/__init__.py
pytrim/call_graph_generator/dependency_resolution/dependency_resolver.py
pytrim/call_graph_generator/dependency_resolution/pypi_resolver/__init__.py
pytrim/call_graph_generator/dependency_resolution/pypi_resolver/entrypoint.py
pytrim/call_graph_generator/partial_cg_generation/merge_json.py
pytrim/call_graph_generator/partial_cg_generation/produce_project_partial_cg.py
pytrim/call_graph_generator/partial_cg_generation/pycg_producer/__init__.py
pytrim/call_graph_generator/partial_cg_generation/pycg_producer/app_producer.py
pytrim/cli/__init__.py
pytrim/cli/cli.py
pytrim/core/__init__.py
pytrim/core/file_remover.py
pytrim/core/report_producer.py
pytrim/extractors/__init__.py
pytrim/extractors/base.py
pytrim/extractors/dependency_extractor.py
pytrim/extractors/docker_files.py
pytrim/extractors/documentation_files.py
pytrim/extractors/ini_files.py
pytrim/extractors/python_files.py
pytrim/extractors/requirements_files.py
pytrim/extractors/shell_files.py
pytrim/extractors/toml_files.py
pytrim/extractors/yaml_files.py
pytrim/removers/__init__.py
pytrim/removers/base.py
pytrim/removers/config_file_remover.py
pytrim/removers/line_utils.py
pytrim/removers/handlers/__init__.py
pytrim/removers/handlers/general_config_remover.py
pytrim/removers/handlers/ini_files_remover.py
pytrim/removers/handlers/requirements_remover.py
pytrim/removers/handlers/system_files_remover.py
pytrim/removers/handlers/yaml_remover.py
pytrim/utils/__init__.py
pytrim/utils/file_patterns.py
pytrim/utils/generate_import_mappings.py
pytrim/utils/package_utils.py
pytrim-0.1.2.dist-info/licenses/LICENSE
pytrim-0.1.2.dist-info/METADATA
pytrim-0.1.2.dist-info/WHEEL
pytrim-0.1.2.dist-info/entry_points.txt
pytrim-0.1.2.dist-info/top_level.txt
pytrim-0.1.2.dist-info/RECORD
