Metadata-Version: 2.4
Name: pytrim
Version: 0.1.2
Summary: Auto-detect and trim unused Python imports and dependencies
Home-page: https://github.com/TrimTeam/PyTrim
Author: Konstantinos Karakatsanis, George Alexopoulos, Giannis Karyotakis, Foivos Proestakis, Evangelos Talos
License: MIT License
Project-URL: Homepage, https://github.com/TrimTeam/PyTrim
Project-URL: Repository, https://github.com/TrimTeam/PyTrim.git
Project-URL: Bug Reports, https://github.com/TrimTeam/PyTrim/issues
Keywords: dependencies,imports,cleanup,trim,python,packaging,optimization,auto-detection,unused
Classifier: Development Status :: 4 - Beta
Classifier: Intended Audience :: Developers
Classifier: License :: OSI Approved :: MIT License
Classifier: Operating System :: OS Independent
Classifier: Programming Language :: Python :: 3
Classifier: Programming Language :: Python :: 3.10
Classifier: Programming Language :: Python :: 3.11
Classifier: Programming Language :: Python :: 3.12
Classifier: Programming Language :: Python :: 3.13
Classifier: Topic :: Software Development :: Libraries :: Python Modules
Classifier: Topic :: Software Development :: Quality Assurance
Classifier: Topic :: System :: Archiving :: Packaging
Requires-Python: >=3.10
License-File: LICENSE
Requires-Dist: tomli>=1.2.0; python_version < "3.11"
Requires-Dist: tqdm>=4.64.0
Requires-Dist: fawltydeps
Requires-Dist: pkginfo
Requires-Dist: flask
Requires-Dist: toml
Requires-Dist: colorama
Provides-Extra: dev
Requires-Dist: pytest>=6.0; extra == "dev"
Requires-Dist: requests; extra == "dev"
Requires-Dist: pre-commit; extra == "dev"
Provides-Extra: docs
Dynamic: home-page
Dynamic: license-file
Dynamic: requires-python
